hond/__init__.py
hond/hond.py
hond/logger.py
hond/metric.py
hond/trigger.py
hond/driver/__init__.py
hond/driver/elasticsearch.py
hond-2.0.5.dist-info/LICENSE.txt
hond-2.0.5.dist-info/METADATA
hond-2.0.5.dist-info/WHEEL
hond-2.0.5.dist-info/top_level.txt
hond-2.0.5.dist-info/RECORD
