Metadata-Version: 2.1
Name: hond
Version: 2.0.5
Summary: Metrics Ingestion and Alerting Reimagined.
Home-page: https://github.com/uptimedog/hond/
Author: Clivern
Author-email: hello@clivern.com
License: MIT
Project-URL: Documentation, https://github.com/uptimedog/hond/
Project-URL: Source, https://github.com/uptimedog/hond/
Project-URL: Changelog, https://github.com/uptimedog/hond/blob/main/CHANGELOG.rst
Project-URL: Tracker, https://github.com/uptimedog/hond/issues
Project-URL: Download, https://pypi.org/project/hond/#files
Platform: any
Classifier: Development Status :: 5 - Production/Stable
Classifier: Programming Language :: Python
Classifier: License :: OSI Approved :: MIT License
License-File: LICENSE.txt
Requires-Dist: elasticsearch <9.0,>8.5
Requires-Dist: requests <3.0,>=2.28
Requires-Dist: importlib-metadata ; python_version < "3.8"
Provides-Extra: testing
Requires-Dist: elasticsearch <9.0,>8.5 ; extra == 'testing'
Requires-Dist: requests <3.0,>=2.28 ; extra == 'testing'
Requires-Dist: setuptools ; extra == 'testing'
Requires-Dist: pytest ; extra == 'testing'
Requires-Dist: pytest-cov ; extra == 'testing'
